{
  "id": "youthline",
  "kind": "resource",
  "slug": "youthline",
  "type": "hotline",
  "name": "YouthLine",
  "summary": "Teen-to-teen crisis support line where young people help other young people.",
  "labels": {
    "free": true,
    "availability": "Hours vary",
    "focus": ["Youth", "Peer Support"],
    "audience": ["Teens", "Young Adults"],
    "verified": true
  },
  "org": {
    "name": "Lines for Life",
    "url": "https://oregonyouthline.org"
  },
  "coverage": [
    {
      "region": "US",
      "scope": "national"
    }
  ],
  "contacts": [
    {
      "region": "US",
      "channels": {
        "call": [
          {
            "label": "Call",
            "value": "1-877-968-8491"
          }
        ],
        "text": [
          {
            "label": "Text teen2teen to",
            "value": "839863"
          }
        ],
        "chat": [
          {
            "label": "Chat",
            "value": null
          }
        ],
        "tty": [],
        "other": []
      }
    }
  ],
  "actions": {
    "site_url": "https://oregonyouthline.org",
    "chat_url": null,
    "text": "839863",
    "tty": null,
    "whatsapp": null
  },
  "i18n": {
    "languages": ["English"],
    "accessibility": []
  },
  "taxonomy": {
    "topics": ["crisis", "peer-support", "youth-support"],
    "conditions": ["crisis", "depression", "anxiety"],
    "identities": ["Youth", "Teens"]
  },
  "search": {
    "keywords": ["youth", "teen", "peer", "young adult", "adolescent"],
    "aka": ["Oregon YouthLine"]
  },
  "linkage": {
    "see_also": ["the-trevor-project", "boys-town-national-hotline"],
    "supersedes": [],
    "superseded_by": []
  },
  "compliance": {
    "last_verified": null,
    "source_of_truth": "public-website",
    "notes": null
  },
  "seo": {
    "indexable": true,
    "canonical": "/crisis/youthline",
    "schema_org": "Organization"
  },
  "display": {
    "pin": false,
    "weight": 0
  },
  "categories": ["youth", "peer-support"]
}
